{
  "updated_at": "2026-06-30T22:53:27+00:00",
  "source": "football-data.org",
  "competition": "WC",
  "teams": [
    {
      "team": "Mexico",
      "group": "Group A",
      "MP": 3,
      "W": 3,
      "D": 0,
      "L": 0,
      "GF": 6,
      "GA": 0,
      "GD": 6,
      "points": 9,
      "win_pct": 100.0
    },
    {
      "team": "South Africa",
      "group": "Group A",
      "MP": 3,
      "W": 1,
      "D": 1,
      "L": 1,
      "GF": 2,
      "GA": 3,
      "GD": -1,
      "points": 4,
      "win_pct": 33.3
    },
    {
      "team": "Korea Republic",
      "group": "Group A",
      "MP": 3,
      "W": 1,
      "D": 0,
      "L": 2,
      "GF": 2,
      "GA": 3,
      "GD": -1,
      "points": 3,
      "win_pct": 33.3
    },
    {
      "team": "Czechia",
      "group": "Group A",
      "MP": 3,
      "W": 0,
      "D": 1,
      "L": 2,
      "GF": 2,
      "GA": 6,
      "GD": -4,
      "points": 1,
      "win_pct": 0.0
    },
    {
      "team": "Switzerland",
      "group": "Group B",
      "MP": 3,
      "W": 2,
      "D": 1,
      "L": 0,
      "GF": 7,
      "GA": 3,
      "GD": 4,
      "points": 7,
      "win_pct": 66.7
    },
    {
      "team": "Canada",
      "group": "Group B",
      "MP": 3,
      "W": 1,
      "D": 1,
      "L": 1,
      "GF": 8,
      "GA": 3,
      "GD": 5,
      "points": 4,
      "win_pct": 33.3
    },
    {
      "team": "Bosnia-H.",
      "group": "Group B",
      "MP": 3,
      "W": 1,
      "D": 1,
      "L": 1,
      "GF": 5,
      "GA": 6,
      "GD": -1,
      "points": 4,
      "win_pct": 33.3
    },
    {
      "team": "Qatar",
      "group": "Group B",
      "MP": 3,
      "W": 0,
      "D": 1,
      "L": 2,
      "GF": 2,
      "GA": 10,
      "GD": -8,
      "points": 1,
      "win_pct": 0.0
    },
    {
      "team": "Brazil",
      "group": "Group C",
      "MP": 3,
      "W": 2,
      "D": 1,
      "L": 0,
      "GF": 7,
      "GA": 1,
      "GD": 6,
      "points": 7,
      "win_pct": 66.7
    },
    {
      "team": "Morocco",
      "group": "Group C",
      "MP": 3,
      "W": 2,
      "D": 1,
      "L": 0,
      "GF": 6,
      "GA": 3,
      "GD": 3,
      "points": 7,
      "win_pct": 66.7
    },
    {
      "team": "Scotland",
      "group": "Group C",
      "MP": 3,
      "W": 1,
      "D": 0,
      "L": 2,
      "GF": 1,
      "GA": 4,
      "GD": -3,
      "points": 3,
      "win_pct": 33.3
    },
    {
      "team": "Haiti",
      "group": "Group C",
      "MP": 3,
      "W": 0,
      "D": 0,
      "L": 3,
      "GF": 2,
      "GA": 8,
      "GD": -6,
      "points": 0,
      "win_pct": 0.0
    },
    {
      "team": "USA",
      "group": "Group D",
      "MP": 3,
      "W": 2,
      "D": 0,
      "L": 1,
      "GF": 8,
      "GA": 4,
      "GD": 4,
      "points": 6,
      "win_pct": 66.7
    },
    {
      "team": "Australia",
      "group": "Group D",
      "MP": 3,
      "W": 1,
      "D": 1,
      "L": 1,
      "GF": 2,
      "GA": 2,
      "GD": 0,
      "points": 4,
      "win_pct": 33.3
    },
    {
      "team": "Paraguay",
      "group": "Group D",
      "MP": 3,
      "W": 1,
      "D": 1,
      "L": 1,
      "GF": 2,
      "GA": 4,
      "GD": -2,
      "points": 4,
      "win_pct": 33.3
    },
    {
      "team": "Turkey",
      "group": "Group D",
      "MP": 3,
      "W": 1,
      "D": 0,
      "L": 2,
      "GF": 3,
      "GA": 5,
      "GD": -2,
      "points": 3,
      "win_pct": 33.3
    },
    {
      "team": "Germany",
      "group": "Group E",
      "MP": 3,
      "W": 2,
      "D": 0,
      "L": 1,
      "GF": 10,
      "GA": 4,
      "GD": 6,
      "points": 6,
      "win_pct": 66.7
    },
    {
      "team": "Ivory Coast",
      "group": "Group E",
      "MP": 3,
      "W": 2,
      "D": 0,
      "L": 1,
      "GF": 4,
      "GA": 2,
      "GD": 2,
      "points": 6,
      "win_pct": 66.7
    },
    {
      "team": "Ecuador",
      "group": "Group E",
      "MP": 3,
      "W": 1,
      "D": 1,
      "L": 1,
      "GF": 2,
      "GA": 2,
      "GD": 0,
      "points": 4,
      "win_pct": 33.3
    },
    {
      "team": "Curaçao",
      "group": "Group E",
      "MP": 3,
      "W": 0,
      "D": 1,
      "L": 2,
      "GF": 1,
      "GA": 9,
      "GD": -8,
      "points": 1,
      "win_pct": 0.0
    },
    {
      "team": "Netherlands",
      "group": "Group F",
      "MP": 3,
      "W": 2,
      "D": 1,
      "L": 0,
      "GF": 10,
      "GA": 4,
      "GD": 6,
      "points": 7,
      "win_pct": 66.7
    },
    {
      "team": "Japan",
      "group": "Group F",
      "MP": 3,
      "W": 1,
      "D": 2,
      "L": 0,
      "GF": 7,
      "GA": 3,
      "GD": 4,
      "points": 5,
      "win_pct": 33.3
    },
    {
      "team": "Sweden",
      "group": "Group F",
      "MP": 3,
      "W": 1,
      "D": 1,
      "L": 1,
      "GF": 7,
      "GA": 7,
      "GD": 0,
      "points": 4,
      "win_pct": 33.3
    },
    {
      "team": "Tunisia",
      "group": "Group F",
      "MP": 3,
      "W": 0,
      "D": 0,
      "L": 3,
      "GF": 2,
      "GA": 12,
      "GD": -10,
      "points": 0,
      "win_pct": 0.0
    },
    {
      "team": "Belgium",
      "group": "Group G",
      "MP": 3,
      "W": 1,
      "D": 2,
      "L": 0,
      "GF": 6,
      "GA": 2,
      "GD": 4,
      "points": 5,
      "win_pct": 33.3
    },
    {
      "team": "Egypt",
      "group": "Group G",
      "MP": 3,
      "W": 1,
      "D": 2,
      "L": 0,
      "GF": 5,
      "GA": 3,
      "GD": 2,
      "points": 5,
      "win_pct": 33.3
    },
    {
      "team": "Iran",
      "group": "Group G",
      "MP": 3,
      "W": 0,
      "D": 3,
      "L": 0,
      "GF": 3,
      "GA": 3,
      "GD": 0,
      "points": 3,
      "win_pct": 0.0
    },
    {
      "team": "New Zealand",
      "group": "Group G",
      "MP": 3,
      "W": 0,
      "D": 1,
      "L": 2,
      "GF": 4,
      "GA": 10,
      "GD": -6,
      "points": 1,
      "win_pct": 0.0
    },
    {
      "team": "Spain",
      "group": "Group H",
      "MP": 3,
      "W": 2,
      "D": 1,
      "L": 0,
      "GF": 5,
      "GA": 0,
      "GD": 5,
      "points": 7,
      "win_pct": 66.7
    },
    {
      "team": "Cape Verde",
      "group": "Group H",
      "MP": 3,
      "W": 0,
      "D": 3,
      "L": 0,
      "GF": 2,
      "GA": 2,
      "GD": 0,
      "points": 3,
      "win_pct": 0.0
    },
    {
      "team": "Uruguay",
      "group": "Group H",
      "MP": 3,
      "W": 0,
      "D": 2,
      "L": 1,
      "GF": 3,
      "GA": 4,
      "GD": -1,
      "points": 2,
      "win_pct": 0.0
    },
    {
      "team": "Saudi Arabia",
      "group": "Group H",
      "MP": 3,
      "W": 0,
      "D": 2,
      "L": 1,
      "GF": 1,
      "GA": 5,
      "GD": -4,
      "points": 2,
      "win_pct": 0.0
    },
    {
      "team": "France",
      "group": "Group I",
      "MP": 3,
      "W": 3,
      "D": 0,
      "L": 0,
      "GF": 10,
      "GA": 2,
      "GD": 8,
      "points": 9,
      "win_pct": 100.0
    },
    {
      "team": "Norway",
      "group": "Group I",
      "MP": 3,
      "W": 2,
      "D": 0,
      "L": 1,
      "GF": 8,
      "GA": 7,
      "GD": 1,
      "points": 6,
      "win_pct": 66.7
    },
    {
      "team": "Senegal",
      "group": "Group I",
      "MP": 3,
      "W": 1,
      "D": 0,
      "L": 2,
      "GF": 8,
      "GA": 6,
      "GD": 2,
      "points": 3,
      "win_pct": 33.3
    },
    {
      "team": "Iraq",
      "group": "Group I",
      "MP": 3,
      "W": 0,
      "D": 0,
      "L": 3,
      "GF": 1,
      "GA": 12,
      "GD": -11,
      "points": 0,
      "win_pct": 0.0
    },
    {
      "team": "Argentina",
      "group": "Group J",
      "MP": 3,
      "W": 3,
      "D": 0,
      "L": 0,
      "GF": 8,
      "GA": 1,
      "GD": 7,
      "points": 9,
      "win_pct": 100.0
    },
    {
      "team": "Austria",
      "group": "Group J",
      "MP": 3,
      "W": 1,
      "D": 1,
      "L": 1,
      "GF": 6,
      "GA": 6,
      "GD": 0,
      "points": 4,
      "win_pct": 33.3
    },
    {
      "team": "Algeria",
      "group": "Group J",
      "MP": 3,
      "W": 1,
      "D": 1,
      "L": 1,
      "GF": 5,
      "GA": 7,
      "GD": -2,
      "points": 4,
      "win_pct": 33.3
    },
    {
      "team": "Jordan",
      "group": "Group J",
      "MP": 3,
      "W": 0,
      "D": 0,
      "L": 3,
      "GF": 3,
      "GA": 8,
      "GD": -5,
      "points": 0,
      "win_pct": 0.0
    },
    {
      "team": "Colombia",
      "group": "Group K",
      "MP": 3,
      "W": 2,
      "D": 1,
      "L": 0,
      "GF": 4,
      "GA": 1,
      "GD": 3,
      "points": 7,
      "win_pct": 66.7
    },
    {
      "team": "Portugal",
      "group": "Group K",
      "MP": 3,
      "W": 1,
      "D": 2,
      "L": 0,
      "GF": 6,
      "GA": 1,
      "GD": 5,
      "points": 5,
      "win_pct": 33.3
    },
    {
      "team": "Congo DR",
      "group": "Group K",
      "MP": 3,
      "W": 1,
      "D": 1,
      "L": 1,
      "GF": 4,
      "GA": 3,
      "GD": 1,
      "points": 4,
      "win_pct": 33.3
    },
    {
      "team": "Uzbekistan",
      "group": "Group K",
      "MP": 3,
      "W": 0,
      "D": 0,
      "L": 3,
      "GF": 2,
      "GA": 11,
      "GD": -9,
      "points": 0,
      "win_pct": 0.0
    },
    {
      "team": "England",
      "group": "Group L",
      "MP": 3,
      "W": 2,
      "D": 1,
      "L": 0,
      "GF": 6,
      "GA": 2,
      "GD": 4,
      "points": 7,
      "win_pct": 66.7
    },
    {
      "team": "Croatia",
      "group": "Group L",
      "MP": 3,
      "W": 2,
      "D": 0,
      "L": 1,
      "GF": 5,
      "GA": 5,
      "GD": 0,
      "points": 6,
      "win_pct": 66.7
    },
    {
      "team": "Ghana",
      "group": "Group L",
      "MP": 3,
      "W": 1,
      "D": 1,
      "L": 1,
      "GF": 2,
      "GA": 2,
      "GD": 0,
      "points": 4,
      "win_pct": 33.3
    },
    {
      "team": "Panama",
      "group": "Group L",
      "MP": 3,
      "W": 0,
      "D": 0,
      "L": 3,
      "GF": 0,
      "GA": 4,
      "GD": -4,
      "points": 0,
      "win_pct": 0.0
    }
  ],
  "players": [
    {
      "player": "Kylian Mbappé",
      "team": "France",
      "nation": "FRA",
      "g": 6,
      "a": 2,
      "pen": 0,
      "played": 4
    },
    {
      "player": "Lionel Messi",
      "team": "Argentina",
      "nation": "ARG",
      "g": 6,
      "a": 0,
      "pen": 0,
      "played": 3
    },
    {
      "player": "Erling Haaland",
      "team": "Norway",
      "nation": "NOR",
      "g": 5,
      "a": 0,
      "pen": 0,
      "played": 4
    },
    {
      "player": "Vinicius Junior",
      "team": "Brazil",
      "nation": "BRA",
      "g": 4,
      "a": 1,
      "pen": 0,
      "played": 4
    },
    {
      "player": "Ousmane Dembélé",
      "team": "France",
      "nation": "FRA",
      "g": 4,
      "a": 2,
      "pen": 0,
      "played": 4
    },
    {
      "player": "Ismael Saibari",
      "team": "Morocco",
      "nation": "MOR",
      "g": 3,
      "a": 0,
      "pen": 0,
      "played": 4
    },
    {
      "player": "Kai Havertz",
      "team": "Germany",
      "nation": "GER",
      "g": 3,
      "a": 0,
      "pen": 1,
      "played": 4
    },
    {
      "player": "Deniz Undav",
      "team": "Germany",
      "nation": "GER",
      "g": 3,
      "a": 2,
      "pen": 0,
      "played": 4
    },
    {
      "player": "Elijah Just",
      "team": "New Zealand",
      "nation": "NEW",
      "g": 3,
      "a": 0,
      "pen": 0,
      "played": 3
    },
    {
      "player": "Yoane Wissa",
      "team": "Congo DR",
      "nation": "CON",
      "g": 3,
      "a": 0,
      "pen": 1,
      "played": 2
    },
    {
      "player": "Harry Kane",
      "team": "England",
      "nation": "ENG",
      "g": 3,
      "a": 0,
      "pen": 1,
      "played": 3
    },
    {
      "player": "Johan Manzambi",
      "team": "Switzerland",
      "nation": "SWI",
      "g": 3,
      "a": 1,
      "pen": 0,
      "played": 3
    },
    {
      "player": "Jonathan David",
      "team": "Canada",
      "nation": "CAN",
      "g": 3,
      "a": 0,
      "pen": 0,
      "played": 4
    },
    {
      "player": "Matheus Cunha",
      "team": "Brazil",
      "nation": "BRA",
      "g": 3,
      "a": 0,
      "pen": 0,
      "played": 4
    },
    {
      "player": "Brian Brobbey",
      "team": "Netherlands",
      "nation": "NET",
      "g": 3,
      "a": 0,
      "pen": 0,
      "played": 4
    },
    {
      "player": "Cody Gakpo",
      "team": "Netherlands",
      "nation": "NET",
      "g": 3,
      "a": 1,
      "pen": 0,
      "played": 4
    },
    {
      "player": "Ismaïla Sarr",
      "team": "Senegal",
      "nation": "SEN",
      "g": 3,
      "a": 1,
      "pen": 0,
      "played": 3
    },
    {
      "player": "Julián Quiñones",
      "team": "Mexico",
      "nation": "COL",
      "g": 2,
      "a": 0,
      "pen": 0,
      "played": 3
    },
    {
      "player": "Cyle Larin",
      "team": "Canada",
      "nation": "CAN",
      "g": 2,
      "a": 0,
      "pen": 0,
      "played": 4
    },
    {
      "player": "Folarin Balogun",
      "team": "USA",
      "nation": "USA",
      "g": 2,
      "a": 0,
      "pen": 0,
      "played": 3
    },
    {
      "player": "Crysencio Summerville",
      "team": "Netherlands",
      "nation": "NET",
      "g": 2,
      "a": 2,
      "pen": 0,
      "played": 4
    },
    {
      "player": "Daichi Kamada",
      "team": "Japan",
      "nation": "JAP",
      "g": 2,
      "a": 0,
      "pen": 0,
      "played": 4
    },
    {
      "player": "Amad Diallo",
      "team": "Ivory Coast",
      "nation": "IVO",
      "g": 2,
      "a": 0,
      "pen": 0,
      "played": 3
    },
    {
      "player": "Yasin Ayari",
      "team": "Sweden",
      "nation": "SWE",
      "g": 2,
      "a": 0,
      "pen": 0,
      "played": 4
    },
    {
      "player": "Maximiliano Araújo",
      "team": "Uruguay",
      "nation": "URU",
      "g": 2,
      "a": 1,
      "pen": 0,
      "played": 3
    },
    {
      "player": "Ramin Rezaeian",
      "team": "Iran",
      "nation": "IRA",
      "g": 2,
      "a": 1,
      "pen": 0,
      "played": 3
    },
    {
      "player": "Bradley Barcola",
      "team": "France",
      "nation": "FRA",
      "g": 2,
      "a": 1,
      "pen": 0,
      "played": 4
    },
    {
      "player": "Marko Arnautovic",
      "team": "Austria",
      "nation": "AUS",
      "g": 2,
      "a": 0,
      "pen": 1,
      "played": 3
    },
    {
      "player": "Jude Bellingham",
      "team": "England",
      "nation": "ENG",
      "g": 2,
      "a": 1,
      "pen": 0,
      "played": 3
    },
    {
      "player": "Daniel Muñoz",
      "team": "Colombia",
      "nation": "COL",
      "g": 2,
      "a": 0,
      "pen": 0,
      "played": 2
    }
  ]
}